Workbook

Sheet README
A1: F_CASH_SECTOR_FILTER_v01
A2: Fortuna-Cash | Sector selection layer | Top-down: Market -> Sector -> Stock -> Entry
A4: PURPOSE | B4: Rank NSE sectors best-to-worst for (a) swing trading and (b) investing, from objective inputs. Sheet is the spec; column keys in Code_Contract map 1:1 to the Fortuna implementation.
A6: SHEET ORDER
A7: 1. Settings | B7: Weights, benchmark returns, thresholds. EDIT HERE to retune the model. Yellow = input.
A8: 2. Data_Input | B8: Raw per-sector data. This is the only sheet you paste numbers into. Yellow = input.
A9: 3. Trading_Score | B9: Computed. Relative Strength / Trend / Volume / Breadth / News. Do not edit.
A10: 4. Investing_Score | B10: Computed. Earnings / Long-term Trend / Valuation / Industry Growth. Do not edit.
A11: 5. Final_Rank | B11: Computed. Side-by-side trading vs investing rank. This is the output.
A12: 6. Metric_Spec | B12: Which metrics work at sector level and how each is measured.
A13: 7. Macro_Map | B13: Macro trigger -> sector lookup. Feeds the News/Catalyst input manually.
A14: 8. Code_Contract | B14: Field names, types, units, sources. Build the Fortuna module from this sheet.
A16: COLOUR LEGEND
A17: Yellow fill / blue text | B17: Input cell. You (or the data feed) write here.
A18: Black text | B18: Formula on this sheet. Do not overwrite.
A19: Green text | B19: Formula pulling from another sheet. Do not overwrite.
A21: UNITS RULE | B21: All percentage fields are stored as PLAIN NUMBERS, not Excel fractions. 12.4 means 12.4%. This matches raw NSE / screener output and keeps the code contract unambiguous. Do not format these cells as Excel percentages.
A23: SCORING METHOD | B23: Two kinds of sub-score, both on a 0-100 scale:
A24: Relative (percentile) | B24: Sector is ranked against the other sectors on that day. Best = 100, worst = 0. Used for Relative Strength, Volume, Earnings Growth, Valuation. Formula: (COUNT - RANK) / (COUNT - 1) * 100.
A25: Absolute (checklist) | B25: Sector is scored against a fixed rule, independent of other sectors. Used for Trend, Breadth, Industry Growth, News. A sector can score 0 even if it is the best of a bad lot.
A27: MANAGEMENT QUALITY | B27: Deliberately absent. Not measurable at sector level. It belongs to the stock-selection stage that runs AFTER this filter.
A29: REFRESH CADENCE | B29: Returns / trend / volume / breadth: weekly (or daily if automated). Earnings: quarterly, after results season. Valuation: monthly. Industry growth: half-yearly.

Sheet Settings
A1: Settings
A2: Yellow cells are inputs. Weights in each block must sum to 100.
A4: BENCHMARK RETURNS (Nifty 50, %)
A5: Nifty 50 return 1M (%) | B5: 0 | C5: Paste from NSE. Used to compute relative strength.
A6: Nifty 50 return 3M (%) | B6: 0
A7: Nifty 50 return 6M (%) | B7: 0
A8: Nifty 50 return 1Y (%) | B8: 0
A10: TRADING WEIGHTS (%)
A11: Relative Strength | B11: 35 | C11: Sector vs Nifty 50. The single most predictive input for swing.
A12: Trend | B12: 25 | C12: Price vs 50/200 EMA + higher-high / higher-low structure.
A13: Volume | B13: 20 | C13: 20d volume expansion + delivery% direction.
A14: Breadth | B14: 15 | C14: % of constituents above 50 EMA. Catches index carried by 2-3 heavyweights.
A15: News / Catalyst | B15: 5 | C15: Manual. Budget, RBI, regulation, commodity shock.
A16: Total (must = 100) | B16: =SUM(B11:B15) -> 100 | C16: =IF(B16=100,"OK","FIX: trading weights do not sum to 100") -> OK
A18: INVESTING WEIGHTS (%)
A19: Earnings Growth | B19: 35 | C19: Aggregate revenue + PAT growth YoY of major constituents.
A20: Long-term Trend | B20: 25 | C20: 1Y return, halved if index is below its 200 EMA.
A21: Valuation | B21: 20 | C21: Sector P/E and P/B vs its OWN 10Y median, not vs other sectors.
A22: Industry Growth | B22: 20 | C22: Manual 1-5 score from industry reports / govt data.
A23: Total (must = 100) | B23: =SUM(B19:B22) -> 100 | C23: =IF(B23=100,"OK","FIX: investing weights do not sum to 100") -> OK
A24: Management Quality | B24: N/A | C24: Not scoreable at sector level. Evaluated per company in the stock-selection stage after this filter.
A26: VERDICT THRESHOLDS (total score)
A27: STRONG if score >= | B27: 65 | C27: Tradeable / investable. Pass to stock-selection stage.
A28: NEUTRAL if score >= | B28: 45 | C28: Watchlist only. No fresh capital.
A29: Below NEUTRAL | B29: AVOID | C29: Blacklist for long entries this cycle.
A31: GATE 0 OVERRIDE
A32: Market regime (1 = risk-on, 0 = risk-off) | B32: 1 | C32: From Fortuna-Cash Gate 0. If 0, every sector verdict is forced to AVOID: in a downtrend the top-ranked sector is only the one falling slowest.

Sheet Data_Input
A1: Data_Input
A2: The ONLY sheet you paste into. All (%) fields are plain numbers: 12.4 means 12.4%.
A4: sector_key | B4: sector_name | C4: nse_index_symbol | D4: ret_1m_pct | E4: ret_3m_pct | F4: ret_6m_pct | G4: ret_1y_pct | H4: close | I4: ema_50 | J4: ema_200 | K4: hh_hl_flag | L4: pct_above_50ema | M4: adv_dec_ratio | N4: vol_ratio_20d | O4: delivery_trend | P4: rev_growth_yoy_pct | Q4: pat_growth_yoy_pct | R4: pe | S4: pe_10y_median | T4: pb | U4: pb_10y_median | V4: industry_growth_1_5 | W4: news_catalyst_m2_p2
A5: BANK | B5: Nifty Bank | C5: NIFTY BANK
A6: FINSRV | B6: Nifty Financial Services | C6: NIFTY FIN SERVICE
A7: PVTBANK | B7: Nifty Private Bank | C7: NIFTY PVT BANK
A8: PSUBANK | B8: Nifty PSU Bank | C8: NIFTY PSU BANK
A9: IT | B9: Nifty IT | C9: NIFTY IT
A10: AUTO | B10: Nifty Auto | C10: NIFTY AUTO
A11: PHARMA | B11: Nifty Pharma | C11: NIFTY PHARMA
A12: HEALTH | B12: Nifty Healthcare | C12: NIFTY HEALTHCARE
A13: FMCG | B13: Nifty FMCG | C13: NIFTY FMCG
A14: METAL | B14: Nifty Metal | C14: NIFTY METAL
A15: REALTY | B15: Nifty Realty | C15: NIFTY REALTY
A16: ENERGY | B16: Nifty Energy | C16: NIFTY ENERGY
... A20: INFRA | B20: Nifty Infrastructure | C20: NIFTY INFRA
A22: EXAMPLE | B22: Format reference only - delete or ignore | D22: 4.2 | E22: 11.8 | F22: 18.4 | G22: 26.1 | H22: 58420 | I22: 56100 | J22: 51200 | K22: 1 | L22: 72 | M22: 1.85 | N22: 1.34 | O22: 1 | P22: 14.2 | Q22: 21.6 | R22: 18.4 | S22: 16.9 | T22: 2.8 | U22: 2.4 | V22: 4 | W22: 1
A24: FIELD NOTES
A25: hh_hl_flag: 1 if the sector index is making higher highs AND higher lows on the daily/weekly chart, else 0.
A26: pct_above_50ema: breadth. Percentage of the sector's constituent stocks trading above their own 50 EMA. 0-100.
A27: adv_dec_ratio: advancing constituents divided by declining constituents, 5-day average. Reference only, not scored in v01.
A28: vol_ratio_20d: last-20-session average volume divided by the previous-20-session average volume. >1 = expansion.
A29: delivery_trend: +1 if sector delivery % is rising over 20 sessions, 0 if flat, -1 if falling.
A30: rev_growth_yoy_pct / pat_growth_yoy_pct: aggregate of the sector's major constituents, latest reported quarter vs same quarter last year.
A31: pe / pb: current sector index valuation. pe_10y_median / pb_10y_median: that sector's own 10-year median. Leave pe blank if the sector aggregate PE is negative.
A32: industry_growth_1_5: manual. 1 = structurally shrinking, 3 = in line with GDP, 5 = multi-year structural tailwind.
A33: news_catalyst_m2_p2: manual. -2 = major sector-wide negative (adverse regulation, commodity shock), 0 = nothing, +2 = major positive (budget allocation, rate cut cycle start).

Sheet Trading_Score
A1: Trading_Score
A2: Computed sheet. Swing / positional horizon. Do not edit.
A4: sector_key | B4: sector_name | C4: rs_1m | D4: rs_3m | E4: rs_6m | F4: rs_raw | G4: rs_score | H4: trend_raw | I4: trend_score | J4: vol_raw | K4: vol_score | L4: breadth_score | M4: news_score | N4: total_score | O4: rank | P4: verdict
A5: =Data_Input!A5 -> BANK | B5: =Data_Input!B5 -> Nifty Bank | C5: =Data_Input!D5-Settings!$B$5 -> 0 | D5: =Data_Input!E5-Settings!$B$6 -> 0 | E5: =Data_Input!F5-Settings!$B$7 -> 0 | F5: =0.5*C5+0.3*D5+0.2*E5 -> 0 | G5: =IFERROR((COUNT($F$5:$F$20)-RANK(F5,$F$5:$F$20))/(COUNT($F$5:$F$20)-1)*100,0) -> 100 | H5: =IF(Data_Input!H5>Data_Input!I5,2,0)+IF(Data_Input!I5>Data_Input!J5,2,0)+IF(Data_Input!H5>Data_Input!J5,1,0)+IF(Data_Input!K5=1,1,0) -> 0 | I5: =H5/6*100 -> 0 | J5: =Data_Input!N5+Data_Input!O5*0.1 -> 0 | K5: =IFERROR((COUNT($J$5:$J$20)-RANK(J5,$J$5:$J$20))/(COUNT($J$5:$J$20)-1)*100,0) -> 100 | L5: =MIN(100,MAX(0,Data_Input!L5)) -> 0 | M5: =(Data_Input!W5+2)/4*100 -> 50 | N5: =(G5*Settings!$B$11+I5*Settings!$B$12+K5*Settings!$B$13+L5*Settings!$B$14+M5*Settings!$B$15)/100 -> 57.5 | O5: =RANK(N5,$N$5:$N$20) -> 1 | P5: =IF(Settings!$B$32=0,"AVOID (Gate 0)",IF(N5>=Settings!$B$27,"STRONG",IF(N5>=Settings!$B$28,"NEUTRAL","AVOID"))) -> NEUTRAL
A6: =Data_Input!A6 -> FINSRV | B6: =Data_Input!B6 -> Nifty Financial Services | C6: =Data_Input!D6-Settings!$B$5 -> 0 | D6: =Data_Input!E6-Settings!$B$6 -> 0 | E6: =Data_Input!F6-Settings!$B$7 -> 0 | F6: =0.5*C6+0.3*D6+0.2*E6 -> 0 | G6: =IFERROR((COUNT($F$5:$F$20)-RANK(F6,$F$5:$F$20))/(COUNT($F$5:$F$20)-1)*100,0) -> 100 | H6: =IF(Data_Input!H6>Data_Input!I6,2,0)+IF(Data_Input!I6>Data_Input!J6,2,0)+IF(Data_Input!H6>Data_Input!J6,1,0)+IF(Data_Input!K6=1,1,0) -> 0 | I6: =H6/6*100 -> 0 | J6: =Data_Input!N6+Data_Input!O6*0.1 -> 0 | K6: =IFERROR((COUNT($J$5:$J$20)-RANK(J6,$J$5:$J$20))/(COUNT($J$5:$J$20)-1)*100,0) -> 100 | L6: =MIN(100,MAX(0,Data_Input!L6)) -> 0 | M6: =(Data_Input!W6+2)/4*100 -> 50 | N6: =(G6*Settings!$B$11+I6*Settings!$B$12+K6*Settings!$B$13+L6*Settings!$B$14+M6*Settings!$B$15)/100 -> 57.5 | O6: =RANK(N6,$N$5:$N$20) -> 1 | P6: =IF(Settings!$B$32=0,"AVOID (Gate 0)",IF(N6>=Settings!$B$27,"STRONG",IF(N6>=Settings!$B$28,"NEUTRAL","AVOID"))) -> NEUTRAL
A7: =Data_Input!A7 -> PVTBANK | B7: =Data_Input!B7 -> Nifty Private Bank | C7: =Data_Input!D7-Settings!$B$5 -> 0 | D7: =Data_Input!E7-Settings!$B$6 -> 0 | E7: =Data_Input!F7-Settings!$B$7 -> 0 | F7: =0.5*C7+0.3*D7+0.2*E7 -> 0 | G7: =IFERROR((COUNT($F$5:$F$20)-RANK(F7,$F$5:$F$20))/(COUNT($F$5:$F$20)-1)*100,0) -> 100 | H7: =IF(Data_Input!H7>Data_Input!I7,2,0)+IF(Data_Input!I7>Data_Input!J7,2,0)+IF(Data_Input!H7>Data_Input!J7,1,0)+IF(Data_Input!K7=1,1,0) -> 0 | I7: =H7/6*100 -> 0 | J7: =Data_Input!N7+Data_Input!O7*0.1 -> 0 | K7: =IFERROR((COUNT($J$5:$J$20)-RANK(J7,$J$5:$J$20))/(COUNT($J$5:$J$20)-1)*100,0) -> 100 | L7: =MIN(100,MAX(0,Data_Input!L7)) -> 0 | M7: =(Data_Input!W7+2)/4*100 -> 50 | N7: =(G7*Settings!$B$11+I7*Settings!$B$12+K7*Settings!$B$13+L7*Settings!$B$14+M7*Settings!$B$15)/100 -> 57.5 | O7: =RANK(N7,$N$5:$N$20) -> 1 | P7: =IF(Settings!$B$32=0,"AVOID (Gate 0)",IF(N7>=Settings!$B$27,"STRONG",IF(N7>=Settings!$B$28,"NEUTRAL","AVOID"))) -> NEUTRAL
A8: =Data_Input!A8 -> PSUBANK | B8: =Data_Input!B8 -> Nifty PSU Bank | C8: =Data_Input!D8-Settings!$B$5 -> 0 | D8: =Data_Input!E8-Settings!$B$6 -> 0 | E8: =Data_Input!F8-Settings!$B$7 -> 0 | F8: =0.5*C8+0.3*D8+0.2*E8 -> 0 | G8: =IFERROR((COUNT($F$5:$F$20)-RANK(F8,$F$5:$F$20))/(COUNT($F$5:$F$20)-1)*100,0) -> 100 | H8: =IF(Data_Input!H8>Data_Input!I8,2,0)+IF(Data_Input!I8>Data_Input!J8,2,0)+IF(Data_Input!H8>Data_Input!J8,1,0)+IF(Data_Input!K8=1,1,0) -> 0 | I8: =H8/6*100 -> 0 | J8: =Data_Input!N8+Data_Input!O8*0.1 -> 0 | K8: =IFERROR((COUNT($J$5:$J$20)-RANK(J8,$J$5:$J$20))/(COUNT($J$5:$J$20)-1)*100,0) -> 100 | L8: =MIN(100,MAX(0,Data_Input!L8)) -> 0 | M8: =(Data_Input!W8+2)/4*100 -> 50 | N8: =(G8*Settings!$B$11+I8*Settings!$B$12+K8*Settings!$B$13+L8*Settings!$B$14+M8*Settings!$B$15)/100 -> 57.5 | O8: =RANK(N8,$N$5:$N$20) -> 1 | P8: =IF(Settings!$B$32=0,"AVOID (Gate 0)",IF(N8>=Settings!$B$27,"STRONG",IF(N8>=Settings!$B$28,"NEUTRAL","AVOID"))) -> NEUTRAL
A9: =Data_Input!A9 -> IT | B9: =Data_Input!B9 -> Nifty IT | C9: =Data_Input!D9-Settings!$B$5 -> 0 | D9: =Data_Input!E9-Settings!$B$6 -> 0 | E9: =Data_Input!F9-Settings!$B$7 -> 0 | F9: =0.5*C9+0.3*D9+0.2*E9 -> 0 | G9: =IFERROR((COUNT($F$5:$F$20)-RANK(F9,$F$5:$F$20))/(COUNT($F$5:$F$20)-1)*100,0) -> 100 | H9: =IF(Data_Input!H9>Data_Input!I9,2,0)+IF(Data_Input!I9>Data_Input!J9,2,0)+IF(Data_Input!H9>Data_Input!J9,1,0)+IF(Data_Input!K9=1,1,0) -> 0 | I9: =H9/6*100 -> 0 | J9: =Data_Input!N9+Data_Input!O9*0.1 -> 0 | K9: =IFERROR((COUNT($J$5:$J$20)-RANK(J9,$J$5:$J$20))/(COUNT($J$5:$J$20)-1)*100,0) -> 100 | L9: =MIN(100,MAX(0,Data_Input!L9)) -> 0 | M9: =(Data_Input!W9+2)/4*100 -> 50 | N9: =(G9*Settings!$B$11+I9*Settings!$B$12+K9*Settings!$B$13+L9*Settings!$B$14+M9*Settings!$B$15)/100 -> 57.5 | O9: =RANK(N9,$N$5:$N$20) -> 1 | P9: =IF(Settings!$B$32=0,"AVOID (Gate 0)",IF(N9>=Settings!$B$27,"STRONG",IF(N9>=Settings!$B$28,"NEUTRAL","AVOID"))) -> NEUTRAL
A10: =Data_Input!A10 -> AUTO | B10: =Data_Input!B10 -> Nifty Auto | C10: =Data_Input!D10-Settings!$B$5 -> 0 | D10: =Data_Input!E10-Settings!$B$6 -> 0 | E10: =Data_Input!F10-Settings!$B$7 -> 0 | F10: =0.5*C10+0.3*D10+0.2*E10 -> 0 | G10: =IFERROR((COUNT($F$5:$F$20)-RANK(F10,$F$5:$F$20))/(COUNT($F$5:$F$20)-1)*100,0) -> 100 | H10: =IF(Data_Input!H10>Data_Input!I10,2,0)+IF(Data_Input!I10>Data_Input!J10,2,0)+IF(Data_Input!H10>Data_Input!J10,1,0)+IF(Data_Input!K10=1,1,0) -> 0 | I10: =H10/6*100 -> 0 | J10: =Data_Input!N10+Data_Input!O10*0.1 -> 0 | K10: =IFERROR((COUNT($J$5:$J$20)-RANK(J10,$J$5:$J$20))/(COUNT($J$5:$J$20)-1)*100,0) -> 100 | L10: =MIN(100,MAX(0,Data_Input!L10)) -> 0 | M10: =(Data_Input!W10+2)/4*100 -> 50 | N10: =(G10*Settings!$B$11+I10*Settings!$B$12+K10*Settings!$B$13+L10*Settings!$B$14+M10*Settings!$B$15)/100 -> 57.5 | O10: =RANK(N10,$N$5:$N$20) -> 1 | P10: =IF(Settings!$B$32=0,"AVOID (Gate 0)",IF(N10>=Settings!$B$27,"STRONG",IF(N10>=Settings!$B$28,"NEUTRAL","AVOID"))) -> NEUTRAL
A11: =Data_Input!A11 -> PHARMA | B11: =Data_Input!B11 -> Nifty Pharma | C11: =Data_Input!D11-Settings!$B$5 -> 0 | D11: =Data_Input!E11-Settings!$B$6 -> 0 | E11: =Data_Input!F11-Settings!$B$7 -> 0 | F11: =0.5*C11+0.3*D11+0.2*E11 -> 0 | G11: =IFERROR((COUNT($F$5:$F$20)-RANK(F11,$F$5:$F$20))/(COUNT($F$5:$F$20)-1)*100,0) -> 100 | H11: =IF(Data_Input!H11>Data_Input!I11,2,0)+IF(Data_Input!I11>Data_Input!J11,2,0)+IF(Data_Input!H11>Data_Input!J11,1,0)+IF(Data_Input!K11=1,1,0) -> 0 | I11: =H11/6*100 -> 0 | J11: =Data_Input!N11+Data_Input!O11*0.1 -> 0 | K11: =IFERROR((COUNT($J$5:$J$20)-RANK(J11,$J$5:$J$20))/(COUNT($J$5:$J$20)-1)*100,0) -> 100 | L11: =MIN(100,MAX(0,Data_Input!L11)) -> 0 | M11: =(Data_Input!W11+2)/4*100 -> 50 | N11: =(G11*Settings!$B$11+I11*Settings!$B$12+K11*Settings!$B$13+L11*Settings!$B$14+M11*Settings!$B$15)/100 -> 57.5 | O11: =RANK(N11,$N$5:$N$20) -> 1 | P11: =IF(Settings!$B$32=0,"AVOID (Gate 0)",IF(N11>=Settings!$B$27,"STRONG",IF(N11>=Settings!$B$28,"NEUTRAL","AVOID"))) -> NEUTRAL
A12: =Data_Input!A12 -> HEALTH | B12: =Data_Input!B12 -> Nifty Healthcare | C12: =Data_Input!D12-Settings!$B$5 -> 0 | D12: =Data_Input!E12-Settings!$B$6 -> 0 | E12: =Data_Input!F12-Settings!$B$7 -> 0 | F12: =0.5*C12+0.3*D12+0.2*E12 -> 0 | G12: =IFERROR((COUNT($F$5:$F$20)-RANK(F12,$F$5:$F$20))/(COUNT($F$5:$F$20)-1)*100,0) -> 100 | H12: =IF(Data_Input!H12>Data_Input!I12,2,0)+IF(Data_Input!I12>Data_Input!J12,2,0)+IF(Data_Input!H12>Data_Input!J12,1,0)+IF(Data_Input!K12=1,1,0) -> 0 | I12: =H12/6*100 -> 0 | J12: =Data_Input!N12+Data_Input!O12*0.1 -> 0 | K12: =IFERROR((COUNT($J$5:$J$20)-RANK(J12,$J$5:$J$20))/(COUNT($J$5:$J$20)-1)*100,0) -> 100 | L12: =MIN(100,MAX(0,Data_Input!L12)) -> 0 | M12: =(Data_Input!W12+2)/4*100 -> 50 | N12: =(G12*Settings!$B$11+I12*Settings!$B$12+K12*Settings!$B$13+L12*Settings!$B$14+M12*Settings!$B$15)/100 -> 57.5 | O12: =RANK(N12,$N$5:$N$20) -> 1 | P12: =IF(Settings!$B$32=0,"AVOID (Gate 0)",IF(N12>=Settings!$B$27,"STRONG",IF(N12>=Settings!$B$28,"NEUTRAL","AVOID"))) -> NEUTRAL
A13: =Data_Input!A13 -> FMCG | B13: =Data_Input!B13 -> Nifty FMCG | C13: =Data_Input!D13-Settings!$B$5 -> 0 | D13: =Data_Input!E13-Settings!$B$6 -> 0 | E13: =Data_Input!F13-Settings!$B$7 -> 0 | F13: =0.5*C13+0.3*D13+0.2*E13 -> 0 | G13: =IFERROR((COUNT($F$5:$F$20)-RANK(F13,$F$5:$F$20))/(COUNT($F$5:$F$20)-1)*100,0) -> 100 | H13: =IF(Data_Input!H13>Data_Input!I13,2,0)+IF(Data_Input!I13>Data_Input!J13,2,0)+IF(Data_Input!H13>Data_Input!J13,1,0)+IF(Data_Input!K13=1,1,0) -> 0 | I13: =H13/6*100 -> 0 | J13: =Data_Input!N13+Data_Input!O13*0.1 -> 0 | K13: =IFERROR((COUNT($J$5:$J$20)-RANK(J13,$J$5:$J$20))/(COUNT($J$5:$J$20)-1)*100,0) -> 100 | L13: =MIN(100,MAX(0,Data_Input!L13)) -> 0 | M13: =(Data_Input!W13+2)/4*100 -> 50 | N13: =(G13*Settings!$B$11+I13*Settings!$B$12+K13*Settings!$B$13+L13*Settings!$B$14+M13*Settings!$B$15)/100 -> 57.5 | O13: =RANK(N13,$N$5:$N$20) -> 1 | P13: =IF(Settings!$B$32=0,"AVOID (Gate 0)",IF(N13>=Settings!$B$27,"STRONG",IF(N13>=Settings!$B$28,"NEUTRAL","AVOID"))) -> NEUTRAL
A14: =Data_Input!A14 -> METAL | B14: =Data_Input!B14 -> Nifty Metal | C14: =Data_Input!D14-Settings!$B$5 -> 0 | D14: =Data_Input!E14-Settings!$B$6 -> 0 | E14: =Data_Input!F14-Settings!$B$7 -> 0 | F14: =0.5*C14+0.3*D14+0.2*E14 -> 0 | G14: =IFERROR((COUNT($F$5:$F$20)-RANK(F14,$F$5:$F$20))/(COUNT($F$5:$F$20)-1)*100,0) -> 100 | H14: =IF(Data_Input!H14>Data_Input!I14,2,0)+IF(Data_Input!I14>Data_Input!J14,2,0)+IF(Data_Input!H14>Data_Input!J14,1,0)+IF(Data_Input!K14=1,1,0) -> 0 | I14: =H14/6*100 -> 0 | J14: =Data_Input!N14+Data_Input!O14*0.1 -> 0 | K14: =IFERROR((COUNT($J$5:$J$20)-RANK(J14,$J$5:$J$20))/(COUNT($J$5:$J$20)-1)*100,0) -> 100 | L14: =MIN(100,MAX(0,Data_Input!L14)) -> 0 | M14: =(Data_Input!W14+2)/4*100 -> 50 | N14: =(G14*Settings!$B$11+I14*Settings!$B$12+K14*Settings!$B$13+L14*Settings!$B$14+M14*Settings!$B$15)/100 -> 57.5 | O14: =RANK(N14,$N$5:$N$20) -> 1 | P14: =IF(Settings!$B$32=0,"AVOID (Gate 0)",IF(N14>=Settings!$B$27,"STRONG",IF(N14>=Settings!$B$28,"NEUTRAL","AVOID"))) -> NEUTRAL
A15: =Data_Input!A15 -> REALTY | B15: =Data_Input!B15 -> Nifty Realty | C15: =Data_Input!D15-Settings!$B$5 -> 0 | D15: =Data_Input!E15-Settings!$B$6 -> 0 | E15: =Data_Input!F15-Settings!$B$7 -> 0 | F15: =0.5*C15+0.3*D15+0.2*E15 -> 0 | G15: =IFERROR((COUNT($F$5:$F$20)-RANK(F15,$F$5:$F$20))/(COUNT($F$5:$F$20)-1)*100,0) -> 100 | H15: =IF(Data_Input!H15>Data_Input!I15,2,0)+IF(Data_Input!I15>Data_Input!J15,2,0)+IF(Data_Input!H15>Data_Input!J15,1,0)+IF(Data_Input!K15=1,1,0) -> 0 | I15: =H15/6*100 -> 0 | J15: =Data_Input!N15+Data_Input!O15*0.1 -> 0 | K15: =IFERROR((COUNT($J$5:$J$20)-RANK(J15,$J$5:$J$20))/(COUNT($J$5:$J$20)-1)*100,0) -> 100 | L15: =MIN(100,MAX(0,Data_Input!L15)) -> 0 | M15: =(Data_Input!W15+2)/4*100 -> 50 | N15: =(G15*Settings!$B$11+I15*Settings!$B$12+K15*Settings!$B$13+L15*Settings!$B$14+M15*Settings!$B$15)/100 -> 57.5 | O15: =RANK(N15,$N$5:$N$20) -> 1 | P15: =IF(Settings!$B$32=0,"AVOID (Gate 0)",IF(N15>=Settings!$B$27,"STRONG",IF(N15>=Settings!$B$28,"NEUTRAL","AVOID"))) -> NEUTRAL
A16: =Data_Input!A16 -> ENERGY | B16: =Data_Input!B16 -> Nifty Energy | C16: =Data_Input!D16-Settings!$B$5 -> 0 | D16: =Data_Input!E16-Settings!$B$6 -> 0 | E16: =Data_Input!F16-Settings!$B$7 -> 0 | F16: =0.5*C16+0.3*D16+0.2*E16 -> 0 | G16: =IFERROR((COUNT($F$5:$F$20)-RANK(F16,$F$5:$F$20))/(COUNT($F$5:$F$20)-1)*100,0) -> 100 | H16: =IF(Data_Input!H16>Data_Input!I16,2,0)+IF(Data_Input!I16>Data_Input!J16,2,0)+IF(Data_Input!H16>Data_Input!J16,1,0)+IF(Data_Input!K16=1,1,0) -> 0 | I16: =H16/6*100 -> 0 | J16: =Data_Input!N16+Data_Input!O16*0.1 -> 0 | K16: =IFERROR((COUNT($J$5:$J$20)-RANK(J16,$J$5:$J$20))/(COUNT($J$5:$J$20)-1)*100,0) -> 100 | L16: =MIN(100,MAX(0,Data_Input!L16)) -> 0 | M16: =(Data_Input!W16+2)/4*100 -> 50 | N16: =(G16*Settings!$B$11+I16*Settings!$B$12+K16*Settings!$B$13+L16*Settings!$B$14+M16*Settings!$B$15)/100 -> 57.5 | O16: =RANK(N16,$N$5:$N$20) -> 1 | P16: =IF(Settings!$B$32=0,"AVOID (Gate 0)",IF(N16>=Settings!$B$27,"STRONG",IF(N16>=Settings!$B$28,"NEUTRAL","AVOID"))) -> NEUTRAL
... A20: =Data_Input!A20 -> INFRA | B20: =Data_Input!B20 -> Nifty Infrastructure | C20: =Data_Input!D20-Settings!$B$5 -> 0 | D20: =Data_Input!E20-Settings!$B$6 -> 0 | E20: =Data_Input!F20-Settings!$B$7 -> 0 | F20: =0.5*C20+0.3*D20+0.2*E20 -> 0 | G20: =IFERROR((COUNT($F$5:$F$20)-RANK(F20,$F$5:$F$20))/(COUNT($F$5:$F$20)-1)*100,0) -> 100 | H20: =IF(Data_Input!H20>Data_Input!I20,2,0)+IF(Data_Input!I20>Data_Input!J20,2,0)+IF(Data_Input!H20>Data_Input!J20,1,0)+IF(Data_Input!K20=1,1,0) -> 0 | I20: =H20/6*100 -> 0 | J20: =Data_Input!N20+Data_Input!O20*0.1 -> 0 | K20: =IFERROR((COUNT($J$5:$J$20)-RANK(J20,$J$5:$J$20))/(COUNT($J$5:$J$20)-1)*100,0) -> 100 | L20: =MIN(100,MAX(0,Data_Input!L20)) -> 0 | M20: =(Data_Input!W20+2)/4*100 -> 50 | N20: =(G20*Settings!$B$11+I20*Settings!$B$12+K20*Settings!$B$13+L20*Settings!$B$14+M20*Settings!$B$15)/100 -> 57.5 | O20: =RANK(N20,$N$5:$N$20) -> 1 | P20: =IF(Settings!$B$32=0,"AVOID (Gate 0)",IF(N20>=Settings!$B$27,"STRONG",IF(N20>=Settings!$B$28,"NEUTRAL","AVOID"))) -> NEUTRAL
A22: rs_raw is a weighted blend: 50% 1M + 30% 3M + 20% 6M relative return. Retune here if the swing holding period changes.
A23: trend_raw is out of 6: price>50EMA (2), 50EMA>200EMA (2), price>200EMA (1), higher-high/higher-low (1).
A24: rs_score and vol_score are percentile ranks across the 16 sectors. trend/breadth/news are absolute 0-100.

Sheet Investing_Score
A1: Investing_Score
A2: Computed sheet. 1-3 year horizon. Do not edit.
A4: sector_key | B4: sector_name | C4: earn_raw | D4: earn_score | E4: lt_raw | F4: lt_gate | G4: lt_score | H4: pe_rel | I4: pb_rel | J4: val_raw | K4: val_score | L4: industry_score | M4: total_score | N4: rank | O4: verdict
A5: =Data_Input!A5 -> BANK | B5: =Data_Input!B5 -> Nifty Bank | C5: =0.4*Data_Input!P5+0.6*Data_Input!Q5 -> 0 | D5: =IFERROR((COUNT($C$5:$C$20)-RANK(C5,$C$5:$C$20))/(COUNT($C$5:$C$20)-1)*100,0) -> 100 | E5: =Data_Input!G5 -> 0 | F5: =IF(Data_Input!H5>Data_Input!J5,1,0.5) -> 0.5 | G5: =IFERROR((COUNT($E$5:$E$20)-RANK(E5,$E$5:$E$20))/(COUNT($E$5:$E$20)-1)*100*F5,0) -> 50 | H5: =IF(OR(Data_Input!R5<=0,Data_Input!S5<=0),"",Data_Input!R5/Data_Input!S5) | I5: =IF(OR(Data_Input!T5<=0,Data_Input!U5<=0),"",Data_Input!T5/Data_Input!U5) | J5: =IF(AND(H5="",I5=""),"",IF(H5="",I5,IF(I5="",H5,(H5+I5)/2))) | K5: =IF(J5="",0,IFERROR((COUNT($J$5:$J$20)-RANK(J5,$J$5:$J$20,1))/(COUNT($J$5:$J$20)-1)*100,0)) -> 0 | L5: =(Data_Input!V5-1)/4*100 -> -25 | M5: =(D5*Settings!$B$19+G5*Settings!$B$20+K5*Settings!$B$21+L5*Settings!$B$22)/100 -> 42.5 | N5: =RANK(M5,$M$5:$M$20) -> 1 | O5: =IF(M5>=Settings!$B$27,"STRONG",IF(M5>=Settings!$B$28,"NEUTRAL","AVOID")) -> AVOID
A6: =Data_Input!A6 -> FINSRV | B6: =Data_Input!B6 -> Nifty Financial Services | C6: =0.4*Data_Input!P6+0.6*Data_Input!Q6 -> 0 | D6: =IFERROR((COUNT($C$5:$C$20)-RANK(C6,$C$5:$C$20))/(COUNT($C$5:$C$20)-1)*100,0) -> 100 | E6: =Data_Input!G6 -> 0 | F6: =IF(Data_Input!H6>Data_Input!J6,1,0.5) -> 0.5 | G6: =IFERROR((COUNT($E$5:$E$20)-RANK(E6,$E$5:$E$20))/(COUNT($E$5:$E$20)-1)*100*F6,0) -> 50 | H6: =IF(OR(Data_Input!R6<=0,Data_Input!S6<=0),"",Data_Input!R6/Data_Input!S6) | I6: =IF(OR(Data_Input!T6<=0,Data_Input!U6<=0),"",Data_Input!T6/Data_Input!U6) | J6: =IF(AND(H6="",I6=""),"",IF(H6="",I6,IF(I6="",H6,(H6+I6)/2))) | K6: =IF(J6="",0,IFERROR((COUNT($J$5:$J$20)-RANK(J6,$J$5:$J$20,1))/(COUNT($J$5:$J$20)-1)*100,0)) -> 0 | L6: =(Data_Input!V6-1)/4*100 -> -25 | M6: =(D6*Settings!$B$19+G6*Settings!$B$20+K6*Settings!$B$21+L6*Settings!$B$22)/100 -> 42.5 | N6: =RANK(M6,$M$5:$M$20) -> 1 | O6: =IF(M6>=Settings!$B$27,"STRONG",IF(M6>=Settings!$B$28,"NEUTRAL","AVOID")) -> AVOID
A7: =Data_Input!A7 -> PVTBANK | B7: =Data_Input!B7 -> Nifty Private Bank | C7: =0.4*Data_Input!P7+0.6*Data_Input!Q7 -> 0 | D7: =IFERROR((COUNT($C$5:$C$20)-RANK(C7,$C$5:$C$20))/(COUNT($C$5:$C$20)-1)*100,0) -> 100 | E7: =Data_Input!G7 -> 0 | F7: =IF(Data_Input!H7>Data_Input!J7,1,0.5) -> 0.5 | G7: =IFERROR((COUNT($E$5:$E$20)-RANK(E7,$E$5:$E$20))/(COUNT($E$5:$E$20)-1)*100*F7,0) -> 50 | H7: =IF(OR(Data_Input!R7<=0,Data_Input!S7<=0),"",Data_Input!R7/Data_Input!S7) | I7: =IF(OR(Data_Input!T7<=0,Data_Input!U7<=0),"",Data_Input!T7/Data_Input!U7) | J7: =IF(AND(H7="",I7=""),"",IF(H7="",I7,IF(I7="",H7,(H7+I7)/2))) | K7: =IF(J7="",0,IFERROR((COUNT($J$5:$J$20)-RANK(J7,$J$5:$J$20,1))/(COUNT($J$5:$J$20)-1)*100,0)) -> 0 | L7: =(Data_Input!V7-1)/4*100 -> -25 | M7: =(D7*Settings!$B$19+G7*Settings!$B$20+K7*Settings!$B$21+L7*Settings!$B$22)/100 -> 42.5 | N7: =RANK(M7,$M$5:$M$20) -> 1 | O7: =IF(M7>=Settings!$B$27,"STRONG",IF(M7>=Settings!$B$28,"NEUTRAL","AVOID")) -> AVOID
A8: =Data_Input!A8 -> PSUBANK | B8: =Data_Input!B8 -> Nifty PSU Bank | C8: =0.4*Data_Input!P8+0.6*Data_Input!Q8 -> 0 | D8: =IFERROR((COUNT($C$5:$C$20)-RANK(C8,$C$5:$C$20))/(COUNT($C$5:$C$20)-1)*100,0) -> 100 | E8: =Data_Input!G8 -> 0 | F8: =IF(Data_Input!H8>Data_Input!J8,1,0.5) -> 0.5 | G8: =IFERROR((COUNT($E$5:$E$20)-RANK(E8,$E$5:$E$20))/(COUNT($E$5:$E$20)-1)*100*F8,0) -> 50 | H8: =IF(OR(Data_Input!R8<=0,Data_Input!S8<=0),"",Data_Input!R8/Data_Input!S8) | I8: =IF(OR(Data_Input!T8<=0,Data_Input!U8<=0),"",Data_Input!T8/Data_Input!U8) | J8: =IF(AND(H8="",I8=""),"",IF(H8="",I8,IF(I8="",H8,(H8+I8)/2))) | K8: =IF(J8="",0,IFERROR((COUNT($J$5:$J$20)-RANK(J8,$J$5:$J$20,1))/(COUNT($J$5:$J$20)-1)*100,0)) -> 0 | L8: =(Data_Input!V8-1)/4*100 -> -25 | M8: =(D8*Settings!$B$19+G8*Settings!$B$20+K8*Settings!$B$21+L8*Settings!$B$22)/100 -> 42.5 | N8: =RANK(M8,$M$5:$M$20) -> 1 | O8: =IF(M8>=Settings!$B$27,"STRONG",IF(M8>=Settings!$B$28,"NEUTRAL","AVOID")) -> AVOID
A9: =Data_Input!A9 -> IT | B9: =Data_Input!B9 -> Nifty IT | C9: =0.4*Data_Input!P9+0.6*Data_Input!Q9 -> 0 | D9: =IFERROR((COUNT($C$5:$C$20)-RANK(C9,$C$5:$C$20))/(COUNT($C$5:$C$20)-1)*100,0) -> 100 | E9: =Data_Input!G9 -> 0 | F9: =IF(Data_Input!H9>Data_Input!J9,1,0.5) -> 0.5 | G9: =IFERROR((COUNT($E$5:$E$20)-RANK(E9,$E$5:$E$20))/(COUNT($E$5:$E$20)-1)*100*F9,0) -> 50 | H9: =IF(OR(Data_Input!R9<=0,Data_Input!S9<=0),"",Data_Input!R9/Data_Input!S9) | I9: =IF(OR(Data_Input!T9<=0,Data_Input!U9<=0),"",Data_Input!T9/Data_Input!U9) | J9: =IF(AND(H9="",I9=""),"",IF(H9="",I9,IF(I9="",H9,(H9+I9)/2))) | K9: =IF(J9="",0,IFERROR((COUNT($J$5:$J$20)-RANK(J9,$J$5:$J$20,1))/(COUNT($J$5:$J$20)-1)*100,0)) -> 0 | L9: =(Data_Input!V9-1)/4*100 -> -25 | M9: =(D9*Settings!$B$19+G9*Settings!$B$20+K9*Settings!$B$21+L9*Settings!$B$22)/100 -> 42.5 | N9: =RANK(M9,$M$5:$M$20) -> 1 | O9: =IF(M9>=Settings!$B$27,"STRONG",IF(M9>=Settings!$B$28,"NEUTRAL","AVOID")) -> AVOID
A10: =Data_Input!A10 -> AUTO | B10: =Data_Input!B10 -> Nifty Auto | C10: =0.4*Data_Input!P10+0.6*Data_Input!Q10 -> 0 | D10: =IFERROR((COUNT($C$5:$C$20)-RANK(C10,$C$5:$C$20))/(COUNT($C$5:$C$20)-1)*100,0) -> 100 | E10: =Data_Input!G10 -> 0 | F10: =IF(Data_Input!H10>Data_Input!J10,1,0.5) -> 0.5 | G10: =IFERROR((COUNT($E$5:$E$20)-RANK(E10,$E$5:$E$20))/(COUNT($E$5:$E$20)-1)*100*F10,0) -> 50 | H10: =IF(OR(Data_Input!R10<=0,Data_Input!S10<=0),"",Data_Input!R10/Data_Input!S10) | I10: =IF(OR(Data_Input!T10<=0,Data_Input!U10<=0),"",Data_Input!T10/Data_Input!U10) | J10: =IF(AND(H10="",I10=""),"",IF(H10="",I10,IF(I10="",H10,(H10+I10)/2))) | K10: =IF(J10="",0,IFERROR((COUNT($J$5:$J$20)-RANK(J10,$J$5:$J$20,1))/(COUNT($J$5:$J$20)-1)*100,0)) -> 0 | L10: =(Data_Input!V10-1)/4*100 -> -25 | M10: =(D10*Settings!$B$19+G10*Settings!$B$20+K10*Settings!$B$21+L10*Settings!$B$22)/100 -> 42.5 | N10: =RANK(M10,$M$5:$M$20) -> 1 | O10: =IF(M10>=Settings!$B$27,"STRONG",IF(M10>=Settings!$B$28,"NEUTRAL","AVOID")) -> AVOID
A11: =Data_Input!A11 -> PHARMA | B11: =Data_Input!B11 -> Nifty Pharma | C11: =0.4*Data_Input!P11+0.6*Data_Input!Q11 -> 0 | D11: =IFERROR((COUNT($C$5:$C$20)-RANK(C11,$C$5:$C$20))/(COUNT($C$5:$C$20)-1)*100,0) -> 100 | E11: =Data_Input!G11 -> 0 | F11: =IF(Data_Input!H11>Data_Input!J11,1,0.5) -> 0.5 | G11: =IFERROR((COUNT($E$5:$E$20)-RANK(E11,$E$5:$E$20))/(COUNT($E$5:$E$20)-1)*100*F11,0) -> 50 | H11: =IF(OR(Data_Input!R11<=0,Data_Input!S11<=0),"",Data_Input!R11/Data_Input!S11) | I11: =IF(OR(Data_Input!T11<=0,Data_Input!U11<=0),"",Data_Input!T11/Data_Input!U11) | J11: =IF(AND(H11="",I11=""),"",IF(H11="",I11,IF(I11="",H11,(H11+I11)/2))) | K11: =IF(J11="",0,IFERROR((COUNT($J$5:$J$20)-RANK(J11,$J$5:$J$20,1))/(COUNT($J$5:$J$20)-1)*100,0)) -> 0 | L11: =(Data_Input!V11-1)/4*100 -> -25 | M11: =(D11*Settings!$B$19+G11*Settings!$B$20+K11*Settings!$B$21+L11*Settings!$B$22)/100 -> 42.5 | N11: =RANK(M11,$M$5:$M$20) -> 1 | O11: =IF(M11>=Settings!$B$27,"STRONG",IF(M11>=Settings!$B$28,"NEUTRAL","AVOID")) -> AVOID
A12: =Data_Input!A12 -> HEALTH | B12: =Data_Input!B12 -> Nifty Healthcare | C12: =0.4*Data_Input!P12+0.6*Data_Input!Q12 -> 0 | D12: =IFERROR((COUNT($C$5:$C$20)-RANK(C12,$C$5:$C$20))/(COUNT($C$5:$C$20)-1)*100,0) -> 100 | E12: =Data_Input!G12 -> 0 | F12: =IF(Data_Input!H12>Data_Input!J12,1,0.5) -> 0.5 | G12: =IFERROR((COUNT($E$5:$E$20)-RANK(E12,$E$5:$E$20))/(COUNT($E$5:$E$20)-1)*100*F12,0) -> 50 | H12: =IF(OR(Data_Input!R12<=0,Data_Input!S12<=0),"",Data_Input!R12/Data_Input!S12) | I12: =IF(OR(Data_Input!T12<=0,Data_Input!U12<=0),"",Data_Input!T12/Data_Input!U12) | J12: =IF(AND(H12="",I12=""),"",IF(H12="",I12,IF(I12="",H12,(H12+I12)/2))) | K12: =IF(J12="",0,IFERROR((COUNT($J$5:$J$20)-RANK(J12,$J$5:$J$20,1))/(COUNT($J$5:$J$20)-1)*100,0)) -> 0 | L12: =(Data_Input!V12-1)/4*100 -> -25 | M12: =(D12*Settings!$B$19+G12*Settings!$B$20+K12*Settings!$B$21+L12*Settings!$B$22)/100 -> 42.5 | N12: =RANK(M12,$M$5:$M$20) -> 1 | O12: =IF(M12>=Settings!$B$27,"STRONG",IF(M12>=Settings!$B$28,"NEUTRAL","AVOID")) -> AVOID
A13: =Data_Input!A13 -> FMCG | B13: =Data_Input!B13 -> Nifty FMCG | C13: =0.4*Data_Input!P13+0.6*Data_Input!Q13 -> 0 | D13: =IFERROR((COUNT($C$5:$C$20)-RANK(C13,$C$5:$C$20))/(COUNT($C$5:$C$20)-1)*100,0) -> 100 | E13: =Data_Input!G13 -> 0 | F13: =IF(Data_Input!H13>Data_Input!J13,1,0.5) -> 0.5 | G13: =IFERROR((COUNT($E$5:$E$20)-RANK(E13,$E$5:$E$20))/(COUNT($E$5:$E$20)-1)*100*F13,0) -> 50 | H13: =IF(OR(Data_Input!R13<=0,Data_Input!S13<=0),"",Data_Input!R13/Data_Input!S13) | I13: =IF(OR(Data_Input!T13<=0,Data_Input!U13<=0),"",Data_Input!T13/Data_Input!U13) | J13: =IF(AND(H13="",I13=""),"",IF(H13="",I13,IF(I13="",H13,(H13+I13)/2))) | K13: =IF(J13="",0,IFERROR((COUNT($J$5:$J$20)-RANK(J13,$J$5:$J$20,1))/(COUNT($J$5:$J$20)-1)*100,0)) -> 0 | L13: =(Data_Input!V13-1)/4*100 -> -25 | M13: =(D13*Settings!$B$19+G13*Settings!$B$20+K13*Settings!$B$21+L13*Settings!$B$22)/100 -> 42.5 | N13: =RANK(M13,$M$5:$M$20) -> 1 | O13: =IF(M13>=Settings!$B$27,"STRONG",IF(M13>=Settings!$B$28,"NEUTRAL","AVOID")) -> AVOID
A14: =Data_Input!A14 -> METAL | B14: =Data_Input!B14 -> Nifty Metal | C14: =0.4*Data_Input!P14+0.6*Data_Input!Q14 -> 0 | D14: =IFERROR((COUNT($C$5:$C$20)-RANK(C14,$C$5:$C$20))/(COUNT($C$5:$C$20)-1)*100,0) -> 100 | E14: =Data_Input!G14 -> 0 | F14: =IF(Data_Input!H14>Data_Input!J14,1,0.5) -> 0.5 | G14: =IFERROR((COUNT($E$5:$E$20)-RANK(E14,$E$5:$E$20))/(COUNT($E$5:$E$20)-1)*100*F14,0) -> 50 | H14: =IF(OR(Data_Input!R14<=0,Data_Input!S14<=0),"",Data_Input!R14/Data_Input!S14) | I14: =IF(OR(Data_Input!T14<=0,Data_Input!U14<=0),"",Data_Input!T14/Data_Input!U14) | J14: =IF(AND(H14="",I14=""),"",IF(H14="",I14,IF(I14="",H14,(H14+I14)/2))) | K14: =IF(J14="",0,IFERROR((COUNT($J$5:$J$20)-RANK(J14,$J$5:$J$20,1))/(COUNT($J$5:$J$20)-1)*100,0)) -> 0 | L14: =(Data_Input!V14-1)/4*100 -> -25 | M14: =(D14*Settings!$B$19+G14*Settings!$B$20+K14*Settings!$B$21+L14*Settings!$B$22)/100 -> 42.5 | N14: =RANK(M14,$M$5:$M$20) -> 1 | O14: =IF(M14>=Settings!$B$27,"STRONG",IF(M14>=Settings!$B$28,"NEUTRAL","AVOID")) -> AVOID
A15: =Data_Input!A15 -> REALTY | B15: =Data_Input!B15 -> Nifty Realty | C15: =0.4*Data_Input!P15+0.6*Data_Input!Q15 -> 0 | D15: =IFERROR((COUNT($C$5:$C$20)-RANK(C15,$C$5:$C$20))/(COUNT($C$5:$C$20)-1)*100,0) -> 100 | E15: =Data_Input!G15 -> 0 | F15: =IF(Data_Input!H15>Data_Input!J15,1,0.5) -> 0.5 | G15: =IFERROR((COUNT($E$5:$E$20)-RANK(E15,$E$5:$E$20))/(COUNT($E$5:$E$20)-1)*100*F15,0) -> 50 | H15: =IF(OR(Data_Input!R15<=0,Data_Input!S15<=0),"",Data_Input!R15/Data_Input!S15) | I15: =IF(OR(Data_Input!T15<=0,Data_Input!U15<=0),"",Data_Input!T15/Data_Input!U15) | J15: =IF(AND(H15="",I15=""),"",IF(H15="",I15,IF(I15="",H15,(H15+I15)/2))) | K15: =IF(J15="",0,IFERROR((COUNT($J$5:$J$20)-RANK(J15,$J$5:$J$20,1))/(COUNT($J$5:$J$20)-1)*100,0)) -> 0 | L15: =(Data_Input!V15-1)/4*100 -> -25 | M15: =(D15*Settings!$B$19+G15*Settings!$B$20+K15*Settings!$B$21+L15*Settings!$B$22)/100 -> 42.5 | N15: =RANK(M15,$M$5:$M$20) -> 1 | O15: =IF(M15>=Settings!$B$27,"STRONG",IF(M15>=Settings!$B$28,"NEUTRAL","AVOID")) -> AVOID
A16: =Data_Input!A16 -> ENERGY | B16: =Data_Input!B16 -> Nifty Energy | C16: =0.4*Data_Input!P16+0.6*Data_Input!Q16 -> 0 | D16: =IFERROR((COUNT($C$5:$C$20)-RANK(C16,$C$5:$C$20))/(COUNT($C$5:$C$20)-1)*100,0) -> 100 | E16: =Data_Input!G16 -> 0 | F16: =IF(Data_Input!H16>Data_Input!J16,1,0.5) -> 0.5 | G16: =IFERROR((COUNT($E$5:$E$20)-RANK(E16,$E$5:$E$20))/(COUNT($E$5:$E$20)-1)*100*F16,0) -> 50 | H16: =IF(OR(Data_Input!R16<=0,Data_Input!S16<=0),"",Data_Input!R16/Data_Input!S16) | I16: =IF(OR(Data_Input!T16<=0,Data_Input!U16<=0),"",Data_Input!T16/Data_Input!U16) | J16: =IF(AND(H16="",I16=""),"",IF(H16="",I16,IF(I16="",H16,(H16+I16)/2))) | K16: =IF(J16="",0,IFERROR((COUNT($J$5:$J$20)-RANK(J16,$J$5:$J$20,1))/(COUNT($J$5:$J$20)-1)*100,0)) -> 0 | L16: =(Data_Input!V16-1)/4*100 -> -25 | M16: =(D16*Settings!$B$19+G16*Settings!$B$20+K16*Settings!$B$21+L16*Settings!$B$22)/100 -> 42.5 | N16: =RANK(M16,$M$5:$M$20) -> 1 | O16: =IF(M16>=Settings!$B$27,"STRONG",IF(M16>=Settings!$B$28,"NEUTRAL","AVOID")) -> AVOID
... A20: =Data_Input!A20 -> INFRA | B20: =Data_Input!B20 -> Nifty Infrastructure | C20: =0.4*Data_Input!P20+0.6*Data_Input!Q20 -> 0 | D20: =IFERROR((COUNT($C$5:$C$20)-RANK(C20,$C$5:$C$20))/(COUNT($C$5:$C$20)-1)*100,0) -> 100 | E20: =Data_Input!G20 -> 0 | F20: =IF(Data_Input!H20>Data_Input!J20,1,0.5) -> 0.5 | G20: =IFERROR((COUNT($E$5:$E$20)-RANK(E20,$E$5:$E$20))/(COUNT($E$5:$E$20)-1)*100*F20,0) -> 50 | H20: =IF(OR(Data_Input!R20<=0,Data_Input!S20<=0),"",Data_Input!R20/Data_Input!S20) | I20: =IF(OR(Data_Input!T20<=0,Data_Input!U20<=0),"",Data_Input!T20/Data_Input!U20) | J20: =IF(AND(H20="",I20=""),"",IF(H20="",I20,IF(I20="",H20,(H20+I20)/2))) | K20: =IF(J20="",0,IFERROR((COUNT($J$5:$J$20)-RANK(J20,$J$5:$J$20,1))/(COUNT($J$5:$J$20)-1)*100,0)) -> 0 | L20: =(Data_Input!V20-1)/4*100 -> -25 | M20: =(D20*Settings!$B$19+G20*Settings!$B$20+K20*Settings!$B$21+L20*Settings!$B$22)/100 -> 42.5 | N20: =RANK(M20,$M$5:$M$20) -> 1 | O20: =IF(M20>=Settings!$B$27,"STRONG",IF(M20>=Settings!$B$28,"NEUTRAL","AVOID")) -> AVOID
A22: earn_raw weights PAT growth 60% and revenue growth 40%. Revenue alone flatters sectors expanding at the cost of margin.
A23: lt_gate halves the long-term trend score when the sector index is below its own 200 EMA, even if the 1Y return is high.
A24: val_raw is the mean of P/E and P/B relative to that sector's OWN 10Y median. Lower is better, so val_score ranks ascending.
A25: Blank pe or pb (negative sector earnings) drops that leg; if both are blank val_score is 0, not neutral. Verify before trusting the rank.
A26: Gate 0 is NOT applied here. A market downtrend is an accumulation opportunity for investing, unlike for swing trading.
A27: Management Quality is deliberately absent. It is a stock-level input for the stage after this filter.

Sheet Final_Rank
A1: Final_Rank
A2: Output sheet. Best to least best. Sort by trade_rank or invest_rank.
A4: sector_key | B4: sector_name | C4: trade_score | D4: trade_rank | E4: trade_verdict | F4: invest_score | G4: invest_rank | H4: invest_verdict | I4: combined_read
A5: =Trading_Score!A5 -> BANK | B5: =Trading_Score!B5 -> Nifty Bank | C5: =Trading_Score!N5 -> 57.5 | D5: =Trading_Score!O5 -> 1 | E5: =Trading_Score!P5 -> NEUTRAL | F5: =Investing_Score!M5 -> 42.5 | G5: =Investing_Score!N5 -> 1 | H5: =Investing_Score!O5 -> AVOID | I5: =IF(AND(C5>=Settings!$B$27,F5>=Settings!$B$27),"Core - trade it and own it",IF(C5>=Settings!$B$27,"Momentum only - trade, do not marry",IF(F5>=Settings!$B$27,"Value setup - accumulate, wait for momentum","Ignore this cycle"))) -> Ignore this cycle
A6: =Trading_Score!A6 -> FINSRV | B6: =Trading_Score!B6 -> Nifty Financial Services | C6: =Trading_Score!N6 -> 57.5 | D6: =Trading_Score!O6 -> 1 | E6: =Trading_Score!P6 -> NEUTRAL | F6: =Investing_Score!M6 -> 42.5 | G6: =Investing_Score!N6 -> 1 | H6: =Investing_Score!O6 -> AVOID | I6: =IF(AND(C6>=Settings!$B$27,F6>=Settings!$B$27),"Core - trade it and own it",IF(C6>=Settings!$B$27,"Momentum only - trade, do not marry",IF(F6>=Settings!$B$27,"Value setup - accumulate, wait for momentum","Ignore this cycle"))) -> Ignore this cycle
A7: =Trading_Score!A7 -> PVTBANK | B7: =Trading_Score!B7 -> Nifty Private Bank | C7: =Trading_Score!N7 -> 57.5 | D7: =Trading_Score!O7 -> 1 | E7: =Trading_Score!P7 -> NEUTRAL | F7: =Investing_Score!M7 -> 42.5 | G7: =Investing_Score!N7 -> 1 | H7: =Investing_Score!O7 -> AVOID | I7: =IF(AND(C7>=Settings!$B$27,F7>=Settings!$B$27),"Core - trade it and own it",IF(C7>=Settings!$B$27,"Momentum only - trade, do not marry",IF(F7>=Settings!$B$27,"Value setup - accumulate, wait for momentum","Ignore this cycle"))) -> Ignore this cycle
A8: =Trading_Score!A8 -> PSUBANK | B8: =Trading_Score!B8 -> Nifty PSU Bank | C8: =Trading_Score!N8 -> 57.5 | D8: =Trading_Score!O8 -> 1 | E8: =Trading_Score!P8 -> NEUTRAL | F8: =Investing_Score!M8 -> 42.5 | G8: =Investing_Score!N8 -> 1 | H8: =Investing_Score!O8 -> AVOID | I8: =IF(AND(C8>=Settings!$B$27,F8>=Settings!$B$27),"Core - trade it and own it",IF(C8>=Settings!$B$27,"Momentum only - trade, do not marry",IF(F8>=Settings!$B$27,"Value setup - accumulate, wait for momentum","Ignore this cycle"))) -> Ignore this cycle
A9: =Trading_Score!A9 -> IT | B9: =Trading_Score!B9 -> Nifty IT | C9: =Trading_Score!N9 -> 57.5 | D9: =Trading_Score!O9 -> 1 | E9: =Trading_Score!P9 -> NEUTRAL | F9: =Investing_Score!M9 -> 42.5 | G9: =Investing_Score!N9 -> 1 | H9: =Investing_Score!O9 -> AVOID | I9: =IF(AND(C9>=Settings!$B$27,F9>=Settings!$B$27),"Core - trade it and own it",IF(C9>=Settings!$B$27,"Momentum only - trade, do not marry",IF(F9>=Settings!$B$27,"Value setup - accumulate, wait for momentum","Ignore this cycle"))) -> Ignore this cycle
A10: =Trading_Score!A10 -> AUTO | B10: =Trading_Score!B10 -> Nifty Auto | C10: =Trading_Score!N10 -> 57.5 | D10: =Trading_Score!O10 -> 1 | E10: =Trading_Score!P10 -> NEUTRAL | F10: =Investing_Score!M10 -> 42.5 | G10: =Investing_Score!N10 -> 1 | H10: =Investing_Score!O10 -> AVOID | I10: =IF(AND(C10>=Settings!$B$27,F10>=Settings!$B$27),"Core - trade it and own it",IF(C10>=Settings!$B$27,"Momentum only - trade, do not marry",IF(F10>=Settings!$B$27,"Value setup - accumulate, wait for momentum","Ignore this cycle"))) -> Ignore this cycle
A11: =Trading_Score!A11 -> PHARMA | B11: =Trading_Score!B11 -> Nifty Pharma | C11: =Trading_Score!N11 -> 57.5 | D11: =Trading_Score!O11 -> 1 | E11: =Trading_Score!P11 -> NEUTRAL | F11: =Investing_Score!M11 -> 42.5 | G11: =Investing_Score!N11 -> 1 | H11: =Investing_Score!O11 -> AVOID | I11: =IF(AND(C11>=Settings!$B$27,F11>=Settings!$B$27),"Core - trade it and own it",IF(C11>=Settings!$B$27,"Momentum only - trade, do not marry",IF(F11>=Settings!$B$27,"Value setup - accumulate, wait for momentum","Ignore this cycle"))) -> Ignore this cycle
A12: =Trading_Score!A12 -> HEALTH | B12: =Trading_Score!B12 -> Nifty Healthcare | C12: =Trading_Score!N12 -> 57.5 | D12: =Trading_Score!O12 -> 1 | E12: =Trading_Score!P12 -> NEUTRAL | F12: =Investing_Score!M12 -> 42.5 | G12: =Investing_Score!N12 -> 1 | H12: =Investing_Score!O12 -> AVOID | I12: =IF(AND(C12>=Settings!$B$27,F12>=Settings!$B$27),"Core - trade it and own it",IF(C12>=Settings!$B$27,"Momentum only - trade, do not marry",IF(F12>=Settings!$B$27,"Value setup - accumulate, wait for momentum","Ignore this cycle"))) -> Ignore this cycle
A13: =Trading_Score!A13 -> FMCG | B13: =Trading_Score!B13 -> Nifty FMCG | C13: =Trading_Score!N13 -> 57.5 | D13: =Trading_Score!O13 -> 1 | E13: =Trading_Score!P13 -> NEUTRAL | F13: =Investing_Score!M13 -> 42.5 | G13: =Investing_Score!N13 -> 1 | H13: =Investing_Score!O13 -> AVOID | I13: =IF(AND(C13>=Settings!$B$27,F13>=Settings!$B$27),"Core - trade it and own it",IF(C13>=Settings!$B$27,"Momentum only - trade, do not marry",IF(F13>=Settings!$B$27,"Value setup - accumulate, wait for momentum","Ignore this cycle"))) -> Ignore this cycle
A14: =Trading_Score!A14 -> METAL | B14: =Trading_Score!B14 -> Nifty Metal | C14: =Trading_Score!N14 -> 57.5 | D14: =Trading_Score!O14 -> 1 | E14: =Trading_Score!P14 -> NEUTRAL | F14: =Investing_Score!M14 -> 42.5 | G14: =Investing_Score!N14 -> 1 | H14: =Investing_Score!O14 -> AVOID | I14: =IF(AND(C14>=Settings!$B$27,F14>=Settings!$B$27),"Core - trade it and own it",IF(C14>=Settings!$B$27,"Momentum only - trade, do not marry",IF(F14>=Settings!$B$27,"Value setup - accumulate, wait for momentum","Ignore this cycle"))) -> Ignore this cycle
A15: =Trading_Score!A15 -> REALTY | B15: =Trading_Score!B15 -> Nifty Realty | C15: =Trading_Score!N15 -> 57.5 | D15: =Trading_Score!O15 -> 1 | E15: =Trading_Score!P15 -> NEUTRAL | F15: =Investing_Score!M15 -> 42.5 | G15: =Investing_Score!N15 -> 1 | H15: =Investing_Score!O15 -> AVOID | I15: =IF(AND(C15>=Settings!$B$27,F15>=Settings!$B$27),"Core - trade it and own it",IF(C15>=Settings!$B$27,"Momentum only - trade, do not marry",IF(F15>=Settings!$B$27,"Value setup - accumulate, wait for momentum","Ignore this cycle"))) -> Ignore this cycle
A16: =Trading_Score!A16 -> ENERGY | B16: =Trading_Score!B16 -> Nifty Energy | C16: =Trading_Score!N16 -> 57.5 | D16: =Trading_Score!O16 -> 1 | E16: =Trading_Score!P16 -> NEUTRAL | F16: =Investing_Score!M16 -> 42.5 | G16: =Investing_Score!N16 -> 1 | H16: =Investing_Score!O16 -> AVOID | I16: =IF(AND(C16>=Settings!$B$27,F16>=Settings!$B$27),"Core - trade it and own it",IF(C16>=Settings!$B$27,"Momentum only - trade, do not marry",IF(F16>=Settings!$B$27,"Value setup - accumulate, wait for momentum","Ignore this cycle"))) -> Ignore this cycle
... A20: =Trading_Score!A20 -> INFRA | B20: =Trading_Score!B20 -> Nifty Infrastructure | C20: =Trading_Score!N20 -> 57.5 | D20: =Trading_Score!O20 -> 1 | E20: =Trading_Score!P20 -> NEUTRAL | F20: =Investing_Score!M20 -> 42.5 | G20: =Investing_Score!N20 -> 1 | H20: =Investing_Score!O20 -> AVOID | I20: =IF(AND(C20>=Settings!$B$27,F20>=Settings!$B$27),"Core - trade it and own it",IF(C20>=Settings!$B$27,"Momentum only - trade, do not marry",IF(F20>=Settings!$B$27,"Value setup - accumulate, wait for momentum","Ignore this cycle"))) -> Ignore this cycle
A22: Feed only STRONG rows into the stock-selection stage. NEUTRAL is watchlist. AVOID is blacklisted for long entries this cycle.
A23: This workbook does not auto-sort. Sort rows 5-20 by trade_rank or invest_rank in Excel, or sort in code before display.

Sheet Metric_Spec
A1: Metric_Spec
A2: Which metrics are measurable at sector level, and how.
A4: metric | B4: used_for | C4: sector_level? | D4: how it is measured | E4: source
A5: Relative Strength | B5: Trading | C5: Yes | D5: Sector index return minus Nifty 50 return over 1M / 3M / 6M. Rising ratio line = outperformance. | E5: NSE indices page
A6: Trend | B6: Trading + Investing | C6: Yes | D6: Sector index chart: price vs 50 EMA and 200 EMA, 50 above 200, higher highs and higher lows. | E6: TradingView / Chartink
A7: Volume | B7: Trading | C7: Mostly | D7: Sector index volume, or average volume of the top constituents. Confirm with delivery % direction. | E7: NSE bhavcopy
A8: Breadth | B8: Trading | C8: Yes | D8: % of constituents above 50 EMA; advancing vs declining count. Guards against a 2-3 stock index move. | E8: Chartink / bhavcopy
A9: News / Catalysts | B9: Trading | C9: Yes | D9: Sector-wide events: budget, RBI policy, regulation, commodity price, global demand. | E9: Manual
A10: Earnings Growth | B10: Investing | C10: Yes | D10: Aggregate revenue and PAT of the sector's major companies, YoY, latest quarter. | E10: Screener / Trendlyne
A11: Long-term Trend | B11: Investing | C11: Yes | D11: Multi-year sector index chart. 1Y return, gated on price above the 200 EMA. | E11: NSE / TradingView
A12: Valuation | B12: Investing | C12: Yes | D12: Sector P/E and P/B against that sector's own 10-year median, not against other sectors. | E12: NSE indices / Trendlyne
A13: Industry Growth | B13: Investing | C13: Yes | D13: Industry reports, government data, sector outlook. Scored 1-5 manually. | E13: Manual
A14: Management Quality | B14: Investing | C14: No | D14: Not measurable for a whole sector. Assessed company by company AFTER the best sector is chosen. | E14: Stock stage, not here
A16: For trading, almost every sector metric can be ranked objectively.
A17: For investing, everything can be ranked except management quality, which is evaluated at the stock stage.

Sheet Macro_Map
A1: Macro_Map
A2: Macro trigger to sector lookup. Drives the manual news_catalyst input.
A4: macro trigger | B4: direction | C4: sectors favoured | D4: sectors hurt
A5: Interest rates | B5: Falling | C5: Bank, Financial Services, Private Bank, Realty, Auto, Consumer Durables | D5: IT (defensive rotation out)
A6: Interest rates | B6: Rising | C6: PSU Bank (NIM expansion early cycle), IT | D6: Realty, Auto, NBFC-heavy Fin Services
A7: Crude oil | B7: Falling | C7: Oil marketing, Paints, Aviation, Tyres, Auto, Consumer Durables | D7: Upstream Oil & Gas, Energy
A8: Crude oil | B8: Rising | C8: Upstream Oil & Gas, Energy | D8: OMC, Paints, Aviation, Auto, Tyres
A9: USD/INR | B9: Rupee weakening | C9: IT, Pharma, Textiles, export-led Metal | D9: Importers, Oil & Gas, Consumer Durables
A10: Government capex | B10: Expanding | C10: Infrastructure, Capital Goods, Cement, Defence, PSU Bank, Metal | D10: -
A11: Monsoon / rural income | B11: Good | C11: FMCG, Auto (tractors, two-wheelers), Consumer Durables, Fertilisers | D11: -
A12: China demand / supply | B12: Demand up, supply cut | C12: Metal, Chemicals | D12: Auto, Consumer Durables (input cost)
A13: Global growth | B13: Slowing | C13: FMCG, Pharma, Healthcare (defensives) | D13: IT, Metal, Energy
A14: Union Budget | B14: Allocation to a sector | C14: The allocated sector (Infra, Defence, Healthcare, Railways) | D14: Sectors facing new levies
A15: Regulation | B15: Tightening | C15: - | D15: The regulated sector (Pharma USFDA, Fin Services, Media)
A16: Inflation | B16: Falling | C16: Consumer Durables, Auto, FMCG (margin relief) | D16: -
A18: Use this to set news_catalyst_m2_p2 in Data_Input. Macro is a confirmation layer, not an entry trigger: it changes conviction and position size, not the signal itself.

Sheet Code_Contract
A1: Code_Contract
A2: Build the Fortuna-Cash sector module from this sheet. Field names match Data_Input headers exactly.
A4: field | B4: type | C4: unit | D4: source | E4: refresh | F4: computation / notes
A5: sector_key | B5: str | C5: - | D5: static | E5: never | F5: Primary key. Uppercase, no spaces.
A6: sector_name | B6: str | C6: - | D6: static | E6: never | F6: Display name.
A7: nse_index_symbol | B7: str | C7: - | D7: static | E7: never | F7: NSE index symbol as returned by nsepython / bhavcopy index file.
A8: ret_1m_pct | B8: float | C8: percent | D8: NSE index history | E8: daily | F8: (close_t / close_t-21 - 1) * 100.
A9: ret_3m_pct | B9: float | C9: percent | D9: NSE index history | E9: daily | F9: 63 sessions.
A10: ret_6m_pct | B10: float | C10: percent | D10: NSE index history | E10: daily | F10: 126 sessions.
A11: ret_1y_pct | B11: float | C11: percent | D11: NSE index history | E11: daily | F11: 252 sessions.
A12: close | B12: float | C12: index pts | D12: NSE index history | E12: daily | F12: Latest close of the sector index.
A13: ema_50 | B13: float | C13: index pts | D13: computed | E13: daily | F13: 50-period EMA on daily closes of the sector index.
A14: ema_200 | B14: float | C14: index pts | D14: computed | E14: daily | F14: 200-period EMA on daily closes.
A15: hh_hl_flag | B15: int | C15: 0 or 1 | D15: computed | E15: daily | F15: 1 if last 2 swing highs ascending AND last 2 swing lows ascending. Swing = 5-bar fractal.
... A27: news_catalyst_m2_p2 | B27: int | C27: -2 to +2 | D27: manual | E27: as it happens | F27: Set from Macro_Map. Decays to 0 after 20 sessions unless renewed.
A29: OUTPUTS
A30: rs_score | B30: float | C30: 0-100 | D30: computed | E30: daily | F30: percentile_rank(0.5*rs_1m + 0.3*rs_3m + 0.2*rs_6m) across sectors, descending.
A31: trend_score | B31: float | C31: 0-100 | D31: computed | E31: daily | F31: ((close>ema50)*2 + (ema50>ema200)*2 + (close>ema200)*1 + hh_hl) / 6 * 100.
A32: vol_score | B32: float | C32: 0-100 | D32: computed | E32: daily | F32: percentile_rank(vol_ratio_20d + 0.10 * delivery_trend), descending.
A33: breadth_score | B33: float | C33: 0-100 | D33: computed | E33: daily | F33: clamp(pct_above_50ema, 0, 100).
A34: news_score | B34: float | C34: 0-100 | D34: computed | E34: event | F34: (news_catalyst + 2) / 4 * 100.
A35: trade_score | B35: float | C35: 0-100 | D35: computed | E35: daily | F35: Weighted sum using Settings trading weights, divided by 100.
A36: earn_score | B36: float | C36: 0-100 | D36: computed | E36: quarterly | F36: percentile_rank(0.4*rev_growth + 0.6*pat_growth), descending.
A37: lt_score | B37: float | C37: 0-100 | D37: computed | E37: daily | F37: percentile_rank(ret_1y) * (1 if close>ema_200 else 0.5).
A38: val_score | B38: float | C38: 0-100 | D38: computed | E38: monthly | F38: percentile_rank(mean(pe/pe_median, pb/pb_median)) ASCENDING. 0 if both legs null.
A39: industry_score | B39: float | C39: 0-100 | D39: computed | E39: half-yearly | F39: (industry_growth_1_5 - 1) / 4 * 100.
A40: invest_score | B40: float | C40: 0-100 | D40: computed | E40: daily | F40: Weighted sum using Settings investing weights, divided by 100.
A41: verdict | B41: enum | C41: - | D41: computed | E41: daily | F41: STRONG >= 65, NEUTRAL >= 45, else AVOID. Trading verdict forced to AVOID when gate0_regime = 0.
A43: HELPER
A44: percentile_rank(x) | B44: func | C44: 0-100 | D44: computed | E44: - | F44: (n - rank(x)) / (n - 1) * 100, where rank 1 = best. Pass ascending=True for metrics where lower is better.
A45: gate0_regime | B45: int | C45: 0 or 1 | D45: Fortuna-Cash Gate 0 | E45: daily | F45: Market mood gate. Sector rank is a relative filter and is not permission to be long.
A47: Order of operations in code: gate0_regime -> load Data_Input fields -> compute sub-scores -> weighted totals -> rank -> verdict -> pass STRONG sectors to stock-selection stage.
